getlongivityai_auth_sdk/__init__.py
getlongivityai_auth_sdk/main.py
getlongivityai_auth_sdk/types.py
getlongivityai_auth_sdk-0.2.3.dist-info/METADATA
getlongivityai_auth_sdk-0.2.3.dist-info/WHEEL
getlongivityai_auth_sdk-0.2.3.dist-info/RECORD
