Metadata-Version: 2.4
Name: getlongivityai-auth-sdk
Version: 0.2.3
Summary: Python Library to intract with Auth Service
Requires-Python: >=3.12
Requires-Dist: httpx>=0.28.1
Requires-Dist: pyjwt>=2.10.1
